hyperx/__init__.py
hyperx/_version.py
hyperx/async_client.py
hyperx/batch.py
hyperx/client.py
hyperx/events.py
hyperx/exceptions.py
hyperx/http.py
hyperx/models.py
hyperx/py.typed
hyperx/query.py
hyperx/agents/__init__.py
hyperx/agents/base.py
hyperx/agents/factory.py
hyperx/agents/langchain.py
hyperx/agents/llamaindex.py
hyperx/agents/quality.py
hyperx/agents/tools/__init__.py
hyperx/agents/tools/crud.py
hyperx/agents/tools/explorer.py
hyperx/agents/tools/lookup.py
hyperx/agents/tools/paths.py
hyperx/agents/tools/search.py
hyperx/cache/__init__.py
hyperx/cache/base.py
hyperx/cache/memory.py
hyperx/cache/redis.py
hyperx/integrations/__init__.py
hyperx/integrations/langchain.py
hyperx/integrations/llamaindex.py
hyperx/resources/__init__.py
hyperx/resources/async_batch.py
hyperx/resources/async_entities.py
hyperx/resources/async_events.py
hyperx/resources/async_hyperedges.py
hyperx/resources/async_paths.py
hyperx/resources/async_search.py
hyperx/resources/async_triggers.py
hyperx/resources/async_webhooks.py
hyperx/resources/batch.py
hyperx/resources/entities.py
hyperx/resources/events.py
hyperx/resources/hyperedges.py
hyperx/resources/paths.py
hyperx/resources/search.py
hyperx/resources/triggers.py
hyperx/resources/webhooks.py
hyperxdb-0.6.0.dist-info/METADATA
hyperxdb-0.6.0.dist-info/WHEEL
hyperxdb-0.6.0.dist-info/licenses/LICENSE
hyperxdb-0.6.0.dist-info/RECORD
