Metadata-Version: 2.4
Name: hyperxdb
Version: 0.6.0
Summary: Python SDK for HyperX - the knowledge layer for AI
Project-URL: Homepage, https://hyperxdb.dev
Project-URL: Documentation, https://hyperxdb.dev/docs
Project-URL: Repository, https://github.com/hyperxdb/hyperx-python
Author-email: HyperX <hello@hyperxdb.dev>
License-Expression: MIT
License-File: LICENSE
Keywords: ai,database,hypergraph,knowledge-graph,rag
Classifier: Development Status :: 3 - Alpha
Classifier: Intended Audience :: Developers
Classifier: License :: OSI Approved :: MIT License
Classifier: Programming Language :: Python :: 3
Classifier: Programming Language :: Python :: 3.10
Classifier: Programming Language :: Python :: 3.11
Classifier: Programming Language :: Python :: 3.12
Classifier: Topic :: Database
Classifier: Topic :: Scientific/Engineering :: Artificial Intelligence
Classifier: Typing :: Typed
Requires-Python: >=3.10
Requires-Dist: httpx>=0.27.0
Requires-Dist: pydantic>=2.0.0
Provides-Extra: all
Requires-Dist: langchain-core>=0.2.0; extra == 'all'
Requires-Dist: llama-index-core>=0.10.0; extra == 'all'
Requires-Dist: redis>=4.0.0; extra == 'all'
Provides-Extra: dev
Requires-Dist: mypy>=1.10.0; extra == 'dev'
Requires-Dist: pytest-asyncio>=0.23.0; extra == 'dev'
Requires-Dist: pytest-httpx>=0.30.0; extra == 'dev'
Requires-Dist: pytest>=8.0.0; extra == 'dev'
Requires-Dist: ruff>=0.4.0; extra == 'dev'
Provides-Extra: langchain
Requires-Dist: langchain-core>=0.2.0; extra == 'langchain'
Provides-Extra: llamaindex
Requires-Dist: llama-index-core>=0.10.0; extra == 'llamaindex'
Provides-Extra: redis
Requires-Dist: redis>=4.0.0; extra == 'redis'
